whittlehurst/__init__.py
whittlehurst/estimateH.py
whittlehurst/generators.py
whittlehurst/spectraldensity.py
whittlehurst-1.2.dist-info/licenses/LICENSE
whittlehurst-1.2.dist-info/METADATA
whittlehurst-1.2.dist-info/WHEEL
whittlehurst-1.2.dist-info/top_level.txt
whittlehurst-1.2.dist-info/RECORD
