Metadata-Version: 2.4
Name: whittlehurst
Version: 1.2
Summary: Hurst exponent estimation using Whittle's method
Home-page: https://github.com/aielte-research/whittlehurst.git
Author: Bálint Csanády
Author-email: csbalint@protonmail.ch
License: MIT
Keywords: hurst,fractional Gaussian noise,fGn,fractional Brownian motion,fBm,ARFIMA,econometrics,time-series
Classifier: Programming Language :: Python :: 3
Classifier: License :: OSI Approved :: MIT License
Classifier: Operating System :: OS Independent
Classifier: Topic :: Scientific/Engineering :: Mathematics
Requires-Python: >3.6
License-File: LICENSE
Requires-Dist: numpy
Requires-Dist: scipy
Requires-Dist: numba==0.62
Dynamic: author
Dynamic: author-email
Dynamic: classifier
Dynamic: description
Dynamic: description-content-type
Dynamic: home-page
Dynamic: keywords
Dynamic: license
Dynamic: license-file
Dynamic: requires-dist
Dynamic: requires-python
Dynamic: summary
